AUTHORS.rst
LICENSE
MANIFEST.in
README.rst
setup.py
django_slowdown.egg-info/PKG-INFO
django_slowdown.egg-info/SOURCES.txt
django_slowdown.egg-info/dependency_links.txt
django_slowdown.egg-info/not-zip-safe
django_slowdown.egg-info/requires.txt
django_slowdown.egg-info/top_level.txt
slowdown/__init__.py
slowdown/middleware.py