Metadata-Version: 1.1
Name: django-slowdown
Version: 0.0.1
Summary: A simple middleware to slow the django response.
Home-page: https://github.com/jespino/django-slowdown
Author: Jesús Espino
Author-email: jespinog@gmail.com
License: UNKNOWN
Platform: UNKNOWN
Classifier: Development Status :: 5 - Production/Stable
Classifier: Programming Language :: Python
Classifier: Operating System :: OS Independent
Classifier: Topic :: Software Development :: Libraries
Classifier: Topic :: Utilities
Classifier: Environment :: Web Environment
Classifier: Framework :: Django
